seqprocessor/__init__.py
seqprocessor/main.py
seqprocessor/mutation/mutation.py
seqprocessor/options.py
seqprocessor/seq/__init__.py
seqprocessor/seq/align.py
seqprocessor/seq/info.py
seqprocessor/seq/phylo.py
seqprocessor/seq/pretreat.py
seqprocessor/seq/translate.py
seqprocessor/utils.py
seqprocessor-0.1.5.dist-info/METADATA
seqprocessor-0.1.5.dist-info/WHEEL
seqprocessor-0.1.5.dist-info/entry_points.txt
seqprocessor-0.1.5.dist-info/RECORD
