Metadata-Version: 2.1
Name: seqprocessor
Version: 0.1.5
Summary: A sequence tool
Author: Ruichen Wang
Author-email: wangruichen100@gmail.com
Requires-Python: >=3.9,<4.0
Classifier: Programming Language :: Python :: 3
Classifier: Programming Language :: Python :: 3.9
Classifier: Programming Language :: Python :: 3.10
Classifier: Programming Language :: Python :: 3.11
Classifier: Programming Language :: Python :: 3.12
Requires-Dist: biopython (>=1.83,<2.0)
Requires-Dist: matplotlib (>=3.7.2,<4.0.0)
Requires-Dist: openpyxl (>=3.1.2,<4.0.0)
Requires-Dist: pandas (>=2.2.2,<3.0.0)
Requires-Dist: requests (>=2.31.0,<3.0.0)
Requires-Dist: tqdm (>=4.65.0,<5.0.0)
Requires-Dist: typer[all] (>=0.12.3,<0.13.0)
Requires-Dist: xlrd (>=2.0.1,<3.0.0)
